better_progress/Bar.py
better_progress/Filler.py
better_progress/Spinner.py
better_progress/_BaseProgress.py
better_progress/_IPrefixSuffix.py
better_progress/__init__.py
better_progress-1.0.4.dist-info/LICENSE
better_progress-1.0.4.dist-info/METADATA
better_progress-1.0.4.dist-info/WHEEL
better_progress-1.0.4.dist-info/top_level.txt
better_progress-1.0.4.dist-info/RECORD
