Metadata-Version: 2.1
Name: better-progress
Version: 1.0.4
Summary: Customize and create a progress bar string.
Home-page: https://github.com/LoganGerber/better-progress
Author: Logan Gerber
Author-email: logangerber1014@yahoo.com
License: UNKNOWN
Platform: UNKNOWN
Classifier: Programming Language :: Python :: 3.5
Classifier: Programming Language :: Python :: 3.6
Classifier: Programming Language :: Python :: 3.7
Classifier: Programming Language :: Python :: 3.8
Classifier: Programming Language :: Python :: 3.9
Classifier: Intended Audience :: Developers
Classifier: License :: OSI Approved :: MIT License
Classifier: Operating System :: OS Independent
Classifier: Typing :: Typed
Classifier: Environment :: Console
Classifier: Development Status :: 5 - Production/Stable
